kas_dagger_utils/__init__.py
kas_dagger_utils/bin/__init__.py
kas_dagger_utils/bin/kas_merge_configs.py
kas_dagger_utils-1.0.0.dist-info/LICENSE
kas_dagger_utils-1.0.0.dist-info/METADATA
kas_dagger_utils-1.0.0.dist-info/WHEEL
kas_dagger_utils-1.0.0.dist-info/entry_points.txt
kas_dagger_utils-1.0.0.dist-info/RECORD
